{"BaseModel.a42ee380-c959-450e-ad29-c840a898cfce": {"__class__": "BaseModel", "created_at": "2017-09-28T21:11:15.504287", "updated_at": "2017-09-28T21:11:15.504296", "id": "a42ee380-c959-450e-ad29-c840a898cfce"}, "BaseModel.af9b4cbd-2ce1-4e6e-8259-f578097dd15f": {"__class__": "BaseModel", "created_at": "2017-09-28T21:11:12.971521", "updated_at": "2017-09-28T21:11:12.971544", "id": "af9b4cbd-2ce1-4e6e-8259-f578097dd15f"}, "BaseModel.be6c56c7-4aff-47db-8f84-e86caf8ba7a6": {"name": "Holberton", "created_at": "2021-02-15T13:29:45.583166", "__class__": "BaseModel", "updated_at": "2021-02-15T13:29:45.583176", "my_number": 89, "id": "be6c56c7-4aff-47db-8f84-e86caf8ba7a6"}, "User.cc3fbc7a-e1e4-491f-b9bf-a01f491ce4e1": {"last_name": "Holberton", "email": "airbnb@holbertonshool.com", "password": "root", "first_name": "Betty", "__class__": "User", "id": "cc3fbc7a-e1e4-491f-b9bf-a01f491ce4e1", "updated_at": "2021-02-15T13:29:45.593785", "created_at": "2021-02-15T13:29:45.593747"}, "BaseModel.38a22b25-ae9c-4fa9-9f94-59b3eb51bfba": {"__class__": "BaseModel", "created_at": "2017-09-28T21:11:13.753337", "updated_at": "2017-09-28T21:11:13.753347", "id": "38a22b25-ae9c-4fa9-9f94-59b3eb51bfba"}, "BaseModel.60476d56-df4b-4c16-bea2-5a49dbace132": {"name": "Holberton", "created_at": "2021-02-15T13:29:45.573606", "__class__": "BaseModel", "updated_at": "2021-02-15T13:29:45.573771", "my_number": 89, "id": "60476d56-df4b-4c16-bea2-5a49dbace132"}, "User.dfaaa52b-0d6a-4395-8e06-9588ef822754": {"created_at": "2021-02-15T13:29:45.604878", "email": "airbnb2@holbertonshool.com", "password": "root", "first_name": "John", "__class__": "User", "updated_at": "2021-02-15T13:29:45.604918", "id": "dfaaa52b-0d6a-4395-8e06-9588ef822754"}, "User.c806da76-7187-4252-9b4c-b513d8e690ed": {"created_at": "2021-02-15T13:29:45.595442", "email": "airbnb2@holbertonshool.com", "password": "root", "first_name": "John", "__class__": "User", "updated_at": "2021-02-15T13:29:45.595492", "id": "c806da76-7187-4252-9b4c-b513d8e690ed"}, "User.3a436ee3-33d3-48c5-9a5f-30049af9b5aa": {"created_at": "2021-02-15T12:33:08.009007", "age": "89", "first_name": "John", "__class__": "User", "updated_at": "2021-02-15T12:33:08.009066", "id": "3a436ee3-33d3-48c5-9a5f-30049af9b5aa"}, "BaseModel.2bf3ebfd-a220-49ee-9ae6-b01c75f6f6a4": {"__class__": "BaseModel", "created_at": "2017-09-28T21:11:14.333852", "updated_at": "2017-09-28T21:11:14.333862", "id": "2bf3ebfd-a220-49ee-9ae6-b01c75f6f6a4"}, "User.a9664f70-486d-4191-bb7a-885296cf4e8b": {"last_name": "Holberton", "email": "airbnb@holbertonshool.com", "password": "root", "first_name": "Betty", "__class__": "User", "id": "a9664f70-486d-4191-bb7a-885296cf4e8b", "updated_at": "2021-02-15T13:29:45.602993", "created_at": "2021-02-15T13:29:45.602969"}}